{
    "burgers": [
        {
            "category_name": "smash",
            "items": [
                {
                    "name": "smash_cheese",
                    "size_upgrades": [
                        {
                            "base_title": "single",
                            "base_size":"m",
                            "base_price": 8.99
                        },
                        {
                            "extra_title": "double",
                            "extra_size": "xl",
                            "extra_price": 2.7
                        }
                    ],
                    "content": "Smashed beef patty, cheddar, pickles, home smash sauce, fresh onion cubes"
                },
                {
                    "name": "smash_bbq",
                    "size_upgrades": [
                        {
                            "base_title": "single",
                            "base_size": "m",
                            "base_price": 9.49
                        },
                        {
                            "extra_title": "double",
                            "extra_size": "xl",
                            "extra_price": 2.7
                        }
                    ],
                    "content": "Smashed Beef Patty, Cheddar, Bacon (Halal), BBQ Sauce, House Sauce, Roasting Onions, Cucumbers, Fresh Onion Cubes"
                },
                {
                    "name": "7th_street_burger",
                    "size_upgrades": [
                        {
                            "title": "single",
                            "size": "m",
                            "base_price": 9.49
                        },
                        {
                            "title": "double",
                            "size": "xl",
                            "extra_price": 2.7
                        }
                    ],
                    "content": "Smashed beef patty, cheddar, pickles, house sauce, home smash sauce, fried onion cubes"
                },
                {
                    "name": "smash_chili_cheese",
                    "size_upgrades": [
                        {
                            "title": "single",
                            "size": "m",
                            "base_price": 9.49
                        },
                        {
                            "title": "double",
                            "size": "xl",
                            "extra_price": 2.7
                        }
                    ],
                    "content": "Smashed Beef Patty, Cheddar, Chili Cheese Sauce, Cucumbers, Home Smash Sauce, Fresh Onion Cubes"
                }
            ]
        },
        {
            "category_name": "classic",
            "items": [
                {
                    "name": "hamburger",
                    "size_upgrades": [
                        {
                            "title": "single",
                            "size": "m",
                            "base_price": 8.99
                        },
                        {
                            "title": "double",
                            "size": "xl",
                            "extra_price": 3.5
                        }
                    ],
                    "content": "Lettuce, tomatoes, cucumbers, red onions and house sauce."
                },
                {
                    "name": "cheeseburger",
                    "size_upgrades": [
                        {
                            "title": "single",
                            "size": "m",
                            "base_price": 10.49
                        },
                        {
                            "title": "double",
                            "size": "xl",
                            "extra_price": 3.5
                        }
                    ],
                    "content": "Salad, tomatoes, cucumbers, red onions, house sauce and cheddar slice."
                },
                {
                    "name": "chili_cheese",
                    "size_upgrades": [
                        {
                            "title": "single",
                            "size": "m",
                            "base_price": 10.79
                        },
                        {
                            "title": "double",
                            "size": "xl",
                            "extra_price": 3.5
                        }
                    ],
                    "content": "Salad, tomatoes, cucumbers, red onions, house sauce, cheddar sauce, cheddar slice and jalapenos."
                },
                {
                    "name": "cheese_bacon",
                    "size_upgrades": [
                        {
                            "title": "single",
                            "size": "m",
                            "base_price": 10.79
                        },
                        {
                            "title": "double",
                            "size": "xl",
                            "extra_price": 3.5
                        }
                    ],
                    "content": "Lettuce, tomatoes, cucumbers, red onions, house sauce, cheddar slice and beef bacon (Helal)."
                },
                {
                    "name": "bbq_bacon",
                    "size_upgrades": [
                        {
                            "title": "single",
                            "size": "m",
                            "base_price": 10.79
                        },
                        {
                            "title": "double",
                            "size": "xl",
                            "extra_price": 3.5
                        }
                    ],
                    "content": "Lettuce, tomatoes, cucumbers, roasted onions, house sauce, BBQ sauce, cheddar slice and beef bacon (halal)."
                },
                {
                    "name": "the_beast",
                    "size_upgrades": [
                        {
                            "title": "triple",
                            "size": "xxl",
                            "base_price": 15.99
                        }
                    ],
                    "content": "3 x beef patty, salad, tomatoes, cucumbers, beef bacon (halal), glazed onions, roasted onions, house sauce, cheddar sauce and cheddar slice."
                },
                {
                    "name": "hollandaise_burger",
                    "size_upgrades": [
                        {
                            "title": "single",
                            "size": "m",
                            "base_price": 10.99
                        },
                        {
                            "title": "double",
                            "size": "xl",
                            "extra_price": 3.5
                        }
                    ],
                    "content": "Lettuce, tomatoes, cucumbers, red onions, Hollandaise sauce and glazed onions."
                }
            ]
        }
    ]
}